[
    {
        "id": 1,
        "vehicleType": "Bike",
        "passengerCapacity": 1,
        "img": "https://cdn5.vectorstock.com/i/thumb-large/58/44/modern-red-motorcycle-motor-vehicle-transport-vector-31775844.jpg",
        "rent": 65
    },
    {
        "id": 2,
        "vehicleType": "Bike",
        "passengerCapacity": 1,
        "img": "https://cdn5.vectorstock.com/i/thumb-large/58/44/modern-red-motorcycle-motor-vehicle-transport-vector-31775844.jpg",
        "rent": 65
    },
    {
        "id": 3,
        "vehicleType": "Bike",
        "passengerCapacity": 1,
        "img": "https://cdn5.vectorstock.com/i/thumb-large/58/44/modern-red-motorcycle-motor-vehicle-transport-vector-31775844.jpg",
        "rent": 65
    },
    {
        "id": 4,
        "vehicleType": "Car",
        "passengerCapacity": 4,
        "img": "https://cdn1.vectorstock.com/i/thumb-large/90/15/a-red-sports-car-vector-21069015.jpg",
        "rent": 70
    },
    {
        "id": 5,
        "vehicleType": "Car",
        "passengerCapacity": 4,
        "img": "https://cdn1.vectorstock.com/i/thumb-large/90/15/a-red-sports-car-vector-21069015.jpg",
        "rent": 70
    },
    {
        "id": 6,
        "vehicleType": "Car",
        "passengerCapacity": 4,
        "img": "https://cdn1.vectorstock.com/i/thumb-large/90/15/a-red-sports-car-vector-21069015.jpg",
        "rent": 70
    },
    {
        "id": 7,
        "vehicleType": "Bus",
        "passengerCapacity": 20,
        "img": "https://cdn4.vectorstock.com/i/thumb-large/56/63/city-bus-vector-4845663.jpg",
        "rent": 120
    },
    {
        "id": 8,
        "vehicleType": "Bus",
        "passengerCapacity": 20,
        "img": "https://cdn4.vectorstock.com/i/thumb-large/56/63/city-bus-vector-4845663.jpg",
        "rent": 120
    },
    {
        "id": 9,
        "vehicleType": "Bus",
        "passengerCapacity": 20,
        "img": "https://cdn4.vectorstock.com/i/thumb-large/56/63/city-bus-vector-4845663.jpg",
        "rent": 120
    },
    {
        "id": 10,
        "vehicleType": "Train",
        "passengerCapacity": 50,
        "img": "https://cdn2.vectorstock.com/i/thumb-large/82/16/speed-modern-high-speed-railway-train-locomotive-vector-19858216.jpg",
        "rent": 220
    },
    {
        "id": 11,
        "vehicleType": "Train",
        "passengerCapacity": 50,
        "img": "https://cdn2.vectorstock.com/i/thumb-large/82/16/speed-modern-high-speed-railway-train-locomotive-vector-19858216.jpg",
        "rent": 220
    },
    {
        "id": 12,
        "vehicleType": "Train",
        "passengerCapacity": 50,
        "img": "https://cdn2.vectorstock.com/i/thumb-large/82/16/speed-modern-high-speed-railway-train-locomotive-vector-19858216.jpg",
        "rent": 220
    }
]